setup.cfg
setup.py
JSONMock.egg-info/PKG-INFO
JSONMock.egg-info/SOURCES.txt
JSONMock.egg-info/dependency_links.txt
JSONMock.egg-info/entry_points.txt
JSONMock.egg-info/requires.txt
JSONMock.egg-info/top_level.txt
jsonmock/__init__.py
jsonmock/__main__.py
jsonmock/database.py
jsonmock/default.py
jsonmock/main.py
jsonmock/message.py
jsonmock/server.py
jsonmock/utils.py