Metadata-Version: 1.0
Name: JSONMock
Version: 0.0.1
Summary: Generate a REST testing server from a json file.
Home-page: https://github.com/lahlali/JSONMock.py
Author: Anass LAHLALI
Author-email: anass.lahlali@hotmail.com
License: UNKNOWN
Keywords: json,REST,server,generate
Platform: UNKNOWN
